myreze/__init__.py
myreze/llm_agent_helper.py
myreze/data/__init__.py
myreze/data/agent_context.py
myreze/data/core.py
myreze/data/geometry.py
myreze/data/validate.py
myreze/data/utils/__init__.py
myreze/data/utils/crop_and_reproject_array.py
myreze/data/utils/geotiff_testing_file.py
myreze/data/utils/unit_conversions.py
myreze/data/utils/zarr_reader.py
myreze/store/__init__.py
myreze/store/product.py
myreze/store/provider.py
myreze/store/server.py
myreze/viz/__init__.py
myreze/viz/visualization.py
myreze/viz/png/__init__.py
myreze/viz/png/geojson_png.py
myreze/viz/png/png.py
myreze/viz/threejs/__init__.py
myreze/viz/threejs/flat_overlay.py
myreze/viz/threejs/geojson_renderer.py
myreze/viz/threejs/png_renderer.py
myreze/viz/threejs/point_data_renderer.py
myreze/viz/threejs/threejs.py
myreze/viz/threejs/trimesh_utilities.py
myreze/viz/tiles/__init__.py
myreze/viz/tiles/xyz.py
myreze/viz/unreal/__init__.py
myreze/viz/unreal/cloudrenderer.py
myreze/viz/unreal/unreal.py
myreze-0.0.10.dist-info/METADATA
myreze-0.0.10.dist-info/WHEEL
myreze-0.0.10.dist-info/top_level.txt
myreze-0.0.10.dist-info/RECORD
