Metadata-Version: 2.4
Name: myreze
Version: 0.0.10
Summary: Placeholder for Myreze data and visualization package
Home-page: 
Author: 
Author-email: Audun Skau Hansen <audunsh4@gmail.com>
Classifier: Programming Language :: Python :: 3
Classifier: License :: OSI Approved :: MIT License
Classifier: Operating System :: OS Independent
Requires-Python: >=3.6
Requires-Dist: trimesh
Requires-Dist: isodate
Requires-Dist: rasterio
Dynamic: requires-python
